robsel/__init__.py
robsel/robsel.py
robust_selection-0.0.8.dist-info/LICENSE.txt
robust_selection-0.0.8.dist-info/METADATA
robust_selection-0.0.8.dist-info/WHEEL
robust_selection-0.0.8.dist-info/top_level.txt
robust_selection-0.0.8.dist-info/RECORD
