Metadata-Version: 2.1
Name: robust-selection
Version: 0.0.8
Summary: Distributionally Robust Formulation and Model Selection for the Graphical Lasso
Home-page: https://github.com/dddlab/robust-selection
Author: Chau Tran
Author-email: chautran@ucsb.edu
License: UNKNOWN
Platform: UNKNOWN
Requires-Python: >=3.6
Requires-Dist: numpy (>=1.15)
Requires-Dist: scikit-learn (>=0.22.1)
